python_env/__init__.py
python_env/create_env.py
python_env/templates/__init__.py
python_env/templates/env.template
python_env/templates/gitignore.template
python_env/templates/setup.template
python_env_starter-0.2.data/scripts/python-env
python_env_starter-0.2.dist-info/DESCRIPTION.rst
python_env_starter-0.2.dist-info/METADATA
python_env_starter-0.2.dist-info/RECORD
python_env_starter-0.2.dist-info/WHEEL
python_env_starter-0.2.dist-info/metadata.json
python_env_starter-0.2.dist-info/top_level.txt
