Metadata-Version: 2.0
Name: python-env-starter
Version: 0.2
Summary: A tool for getting setup with a common automatic python environment
Home-page: https://github.com/markkohdev/python-env
Author: Mark Koh
Author-email: markkohdev@gmail.com
License: MIT
Keywords: env environment autoenv setuptools development
Platform: UNKNOWN
Classifier: Development Status :: 4 - Beta
Classifier: Intended Audience :: Developers
Classifier: Topic :: Software Development :: Build Tools
Classifier: License :: OSI Approved :: MIT License
Classifier: Programming Language :: Python :: 3.4
Classifier: Programming Language :: Python :: 3.5
Classifier: Programming Language :: Python :: 3.6
Requires-Dist: Jinja2 (==2.9.6)
Requires-Dist: future (==0.16.0)
